gpiod/__init__.py
gpiod/py.typed
gpiod/kernel/__init__.py
gpiod/kernel/gpio_h.py
gpiod/kernel/ioctl_h.py
gpiod/libgpiod/__init__.py
gpiod/libgpiod/gpiod_h.py
gpiod/libgpiodcxx/__init__.py
gpiod/test/__init__.py
gpiod/test/blink.py
gpiod/test/bulk_blink.py
gpiod/test/bulk_button.py
gpiod/test/button.py
gpiod/test/sequential_blink.py
gpiod-1.5.3.dist-info/LICENSE.txt
gpiod-1.5.3.dist-info/METADATA
gpiod-1.5.3.dist-info/WHEEL
gpiod-1.5.3.dist-info/top_level.txt
gpiod-1.5.3.dist-info/RECORD
