Metadata-Version: 2.1
Name: gpiod
Version: 1.5.3
Home-page: https://github.com/hhk7734/python3-gpiod
Author: Hyeonki Hong
Author-email: hhk7734@gmail.com
License: MIT
Project-URL: Documentation, https://wiki.loliot.net/docs/lang/python/libraries/gpiod/python-gpiod-about
Project-URL: "Source Code", https://github.com/hhk7734/python3-gpiod
Keywords: GPIO,gpiod
Classifier: Programming Language :: Python :: 3
Classifier: License :: OSI Approved :: MIT License
Classifier: Operating System :: POSIX :: Linux
Classifier: Intended Audience :: Developers
Classifier: Topic :: Software Development
Classifier: Topic :: System :: Hardware
License-File: LICENSE.txt
